geowidgets/__init__.py
geowidgets/geowidgets.py
django_geowidgets-0.1.2.dist-info/LICENSE
django_geowidgets-0.1.2.dist-info/METADATA
django_geowidgets-0.1.2.dist-info/WHEEL
django_geowidgets-0.1.2.dist-info/top_level.txt
django_geowidgets-0.1.2.dist-info/RECORD
