Metadata-Version: 2.1
Name: django-geowidgets
Version: 0.1.2
Summary: Simple widgets for GeoDjango
Home-page: https://github.com/openmeteo/django-geowidgets
Author: Antonis Christofides
Author-email: antonis@antonischristofides.com
License: GNU General Public License v3
Keywords: geowidgets
Classifier: Development Status :: 2 - Pre-Alpha
Classifier: Intended Audience :: Developers
Classifier: License :: OSI Approved :: GNU General Public License v3 (GPLv3)
Classifier: Natural Language :: English
Classifier: Programming Language :: Python :: 3.9
Classifier: Programming Language :: Python :: 3.10
Classifier: Programming Language :: Python :: 3.11
Classifier: Programming Language :: Python :: 3.12
License-File: LICENSE
Requires-Dist: django <6,>=3.2
